RestClient/RestApi.py
RestClient/__init__.py
RestClient/AuthHandling/BasicAuth.py
RestClient/AuthHandling/X509Auth.py
RestClient/ErrorHandling/RestClientExceptions.py
RestClient/ErrorHandling/__init__.py
RestClient/ProxyPlugins/Socks5Proxy.py
RestClient/ProxyPlugins/__init__.py
RestClient/RequestHandling/HTTPRequest.py
RestClient/RequestHandling/HTTPResponse.py
RestClient/RequestHandling/__init__.py
dbs3_pycurl-3.18.3.dist-info/LICENSE
dbs3_pycurl-3.18.3.dist-info/METADATA
dbs3_pycurl-3.18.3.dist-info/WHEEL
dbs3_pycurl-3.18.3.dist-info/top_level.txt
dbs3_pycurl-3.18.3.dist-info/RECORD
